torchtrain/__init__.py
torchtrain/module.py
torchtrain/variable_data_loader.py
torch_train-0.0.3.dist-info/LICENSE
torch_train-0.0.3.dist-info/METADATA
torch_train-0.0.3.dist-info/WHEEL
torch_train-0.0.3.dist-info/top_level.txt
torch_train-0.0.3.dist-info/RECORD
