Metadata-Version: 2.1
Name: torch-train
Version: 0.0.3
Summary: Training wrapper around torch.nn.Module, provides scikit-learn like fit and predict interfaces.
Home-page: https://github.com/Thijsvanede/torch-train
Author: Thijs van Ede
Author-email: t.s.vanede@utwente.nl
License: UNKNOWN
Platform: UNKNOWN
Classifier: Programming Language :: Python :: 3
Classifier: License :: OSI Approved :: MIT License
Classifier: Operating System :: OS Independent
